hovercal/__init__.py
hovercal/prep.py
hovercal/viz.py
hovercal-0.1.0.dist-info/LICENSE
hovercal-0.1.0.dist-info/METADATA
hovercal-0.1.0.dist-info/WHEEL
hovercal-0.1.0.dist-info/top_level.txt
hovercal-0.1.0.dist-info/RECORD
